{
  "version": "v1",
  "blocklist": [],
  "data": [
    {
      "schema_version": "1.0.0",
      "id": "dlg_blender_addon",
      "name": "Darklight Games Blender Tools",
      "tagline": "A toolbox for animations",
      "version": "1.0.2",
      "type": "add-on",
      "maintainer": "Yurii Ti <mooncats@tutanota.com>",
      "license": [
        "SPDX:GPL-3.0-or-later"
      ],
      "blender_version_min": "4.2.0",
      "website": "https://github.com/DarklightGames/dlg_blender_addon",
      "tags": [
        "Animation"
      ],
      "archive_url": "https://github.com/shiftycats/dlg_blender_addon/releases/download/1.0.2/dlg_blender_addon-1.0.2.zip",
      "archive_size": 10289,
      "archive_hash": "sha256:f762bebee39d9bd03ed5231776fe076e2ee3270ef2c940909349ef75fe147fa9"
    }
  ]
}